fzip/__init__.py
fzip/apicep.py
fzip/correios.py
fzip/viacep.py
fzip/zcode.py
fzip-0.0.5.dist-info/LICENSE
fzip-0.0.5.dist-info/METADATA
fzip-0.0.5.dist-info/WHEEL
fzip-0.0.5.dist-info/top_level.txt
fzip-0.0.5.dist-info/RECORD
