Metadata-Version: 2.1
Name: fzip
Version: 0.0.5
Summary: package to cep requests
Home-page: https://github.com/JohnnyDev2001/fast_zipcode
Author: Johnny Rocha
Author-email: johnny.devcode@gmail.com
License: MIT
Platform: UNKNOWN
Classifier: Programming Language :: Python :: 3
Classifier: Operating System :: OS Independent
Requires-Python: >=3.9
License-File: LICENSE
